LICENSE.txt
MANIFEST.in
README.rst
prep.py
setup.py
prep.egg-info/PKG-INFO
prep.egg-info/SOURCES.txt
prep.egg-info/dependency_links.txt
prep.egg-info/entry_points.txt
prep.egg-info/top_level.txt
sample/other.cfg
sample/prep.cfg
sample/conf/sample.cfg
sample/prep.d/logging.inc
sample/prep.d/other.cfg.in
sample/prep.d/sample.cfg.in