Metadata-Version: 1.0
Name: prep
Version: 0.1.3
Summary: Pre-deployment configuration parser/generator
Home-page: https://github.com/ex-nerd/prep
Author: Chris Petersen
Author-email: geek@ex-nerd.com
License: Modified BSD
Platform: UNKNOWN
Classifier: Development Status :: 3 - Alpha
Classifier: Environment :: Web Environment
Classifier: Intended Audience :: Developers
Classifier: License :: OSI Approved :: BSD License
Classifier: Operating System :: OS Independent
Classifier: Programming Language :: Python
Classifier: Environment :: Console
Classifier: Topic :: Utilities
